{
  "Howto_edit_input_file_type": {
    "precision": 1.0,
    "recall": 1.0,
    "f1-score": 1.0,
    "support": 5,
    "confused_with": {}
  },
  "Howto_edit_product_sub-version": {
    "precision": 1.0,
    "recall": 1.0,
    "f1-score": 1.0,
    "support": 6,
    "confused_with": {}
  },
  "Howto_edit_context_file_name": {
    "precision": 1.0,
    "recall": 1.0,
    "f1-score": 1.0,
    "support": 6,
    "confused_with": {}
  },
  "Howto_change_file_type": {
    "precision": 1.0,
    "recall": 1.0,
    "f1-score": 1.0,
    "support": 6,
    "confused_with": {}
  },
  "Howto_submit_json": {
    "precision": 1.0,
    "recall": 1.0,
    "f1-score": 1.0,
    "support": 9,
    "confused_with": {}
  },
  "deny": {
    "precision": 1.0,
    "recall": 1.0,
    "f1-score": 1.0,
    "support": 7,
    "confused_with": {}
  },
  "howto_save_tree": {
    "precision": 1.0,
    "recall": 1.0,
    "f1-score": 1.0,
    "support": 6,
    "confused_with": {}
  },
  "affirm": {
    "precision": 1.0,
    "recall": 1.0,
    "f1-score": 1.0,
    "support": 6,
    "confused_with": {}
  },
  "howto_undo_changes": {
    "precision": 1.0,
    "recall": 1.0,
    "f1-score": 1.0,
    "support": 13,
    "confused_with": {}
  },
  "get_started": {
    "precision": 1.0,
    "recall": 1.0,
    "f1-score": 1.0,
    "support": 15,
    "confused_with": {}
  },
  "Howto_create_group_name": {
    "precision": 1.0,
    "recall": 1.0,
    "f1-score": 1.0,
    "support": 6,
    "confused_with": {}
  },
  "greet": {
    "precision": 0.9285714285714286,
    "recall": 1.0,
    "f1-score": 0.962962962962963,
    "support": 13,
    "confused_with": {}
  },
  "Howto_change_name_of_json": {
    "precision": 1.0,
    "recall": 1.0,
    "f1-score": 1.0,
    "support": 12,
    "confused_with": {}
  },
  "howto_apply_filters": {
    "precision": 1.0,
    "recall": 1.0,
    "f1-score": 1.0,
    "support": 15,
    "confused_with": {}
  },
  "bot_challenge": {
    "precision": 1.0,
    "recall": 1.0,
    "f1-score": 1.0,
    "support": 4,
    "confused_with": {}
  },
  "learn_create_tree_features": {
    "precision": 1.0,
    "recall": 1.0,
    "f1-score": 1.0,
    "support": 14,
    "confused_with": {}
  },
  "Howto_create_new_test_group": {
    "precision": 1.0,
    "recall": 1.0,
    "f1-score": 1.0,
    "support": 14,
    "confused_with": {}
  },
  "Howto_toggle": {
    "precision": 1.0,
    "recall": 1.0,
    "f1-score": 1.0,
    "support": 10,
    "confused_with": {}
  },
  "howto_make_new_tree": {
    "precision": 1.0,
    "recall": 1.0,
    "f1-score": 1.0,
    "support": 11,
    "confused_with": {}
  },
  "mood_unhappy": {
    "precision": 1.0,
    "recall": 1.0,
    "f1-score": 1.0,
    "support": 14,
    "confused_with": {}
  },
  "Howto_remove_json": {
    "precision": 1.0,
    "recall": 1.0,
    "f1-score": 1.0,
    "support": 8,
    "confused_with": {}
  },
  "Howto_edit_json": {
    "precision": 1.0,
    "recall": 1.0,
    "f1-score": 1.0,
    "support": 6,
    "confused_with": {}
  },
  "howto_rename_node": {
    "precision": 1.0,
    "recall": 1.0,
    "f1-score": 1.0,
    "support": 12,
    "confused_with": {}
  },
  "howto_select_tree": {
    "precision": 0.9166666666666666,
    "recall": 1.0,
    "f1-score": 0.9565217391304348,
    "support": 11,
    "confused_with": {}
  },
  "howto_download_tree": {
    "precision": 1.0,
    "recall": 0.8571428571428571,
    "f1-score": 0.923076923076923,
    "support": 7,
    "confused_with": {
      "howto_select_tree": 1
    }
  },
  "mood_great": {
    "precision": 1.0,
    "recall": 1.0,
    "f1-score": 1.0,
    "support": 14,
    "confused_with": {}
  },
  "Howto_edit_input_file_name": {
    "precision": 1.0,
    "recall": 1.0,
    "f1-score": 1.0,
    "support": 6,
    "confused_with": {}
  },
  "learn_image_modulation_features": {
    "precision": 1.0,
    "recall": 1.0,
    "f1-score": 1.0,
    "support": 13,
    "confused_with": {}
  },
  "Howto_refresh_test_case_groups": {
    "precision": 1.0,
    "recall": 1.0,
    "f1-score": 1.0,
    "support": 10,
    "confused_with": {}
  },
  "Howto_output_file_name": {
    "precision": 1.0,
    "recall": 1.0,
    "f1-score": 1.0,
    "support": 6,
    "confused_with": {}
  },
  "howto_delete_tree": {
    "precision": 1.0,
    "recall": 1.0,
    "f1-score": 1.0,
    "support": 12,
    "confused_with": {}
  },
  "howto_delete_a_node": {
    "precision": 1.0,
    "recall": 1.0,
    "f1-score": 1.0,
    "support": 10,
    "confused_with": {}
  },
  "howto_download_image": {
    "precision": 1.0,
    "recall": 1.0,
    "f1-score": 1.0,
    "support": 13,
    "confused_with": {}
  },
  "howto_upload_image": {
    "precision": 1.0,
    "recall": 1.0,
    "f1-score": 1.0,
    "support": 13,
    "confused_with": {}
  },
  "many": {
    "precision": 1.0,
    "recall": 1.0,
    "f1-score": 1.0,
    "support": 6,
    "confused_with": {}
  },
  "Howto_browse_json_files": {
    "precision": 1.0,
    "recall": 1.0,
    "f1-score": 1.0,
    "support": 10,
    "confused_with": {}
  },
  "Howto_execute_test_case": {
    "precision": 1.0,
    "recall": 1.0,
    "f1-score": 1.0,
    "support": 11,
    "confused_with": {}
  },
  "howto_create_child_node": {
    "precision": 1.0,
    "recall": 1.0,
    "f1-score": 1.0,
    "support": 10,
    "confused_with": {}
  },
  "howto_reset_image": {
    "precision": 1.0,
    "recall": 1.0,
    "f1-score": 1.0,
    "support": 13,
    "confused_with": {}
  },
  "goodbye": {
    "precision": 1.0,
    "recall": 0.9090909090909091,
    "f1-score": 0.9523809523809523,
    "support": 11,
    "confused_with": {
      "greet": 1
    }
  },
  "start_tree_build": {
    "precision": 1.0,
    "recall": 1.0,
    "f1-score": 1.0,
    "support": 11,
    "confused_with": {}
  },
  "Learnto_execute_action": {
    "precision": 1.0,
    "recall": 1.0,
    "f1-score": 1.0,
    "support": 11,
    "confused_with": {}
  },
  "Howto_view_test_groups_in_full_screen": {
    "precision": 1.0,
    "recall": 1.0,
    "f1-score": 1.0,
    "support": 10,
    "confused_with": {}
  },
  "Howto_edit_product_version": {
    "precision": 1.0,
    "recall": 1.0,
    "f1-score": 1.0,
    "support": 6,
    "confused_with": {}
  },
  "only_one": {
    "precision": 1.0,
    "recall": 1.0,
    "f1-score": 1.0,
    "support": 5,
    "confused_with": {}
  },
  "accuracy": 0.9954233409610984,
  "macro avg": {
    "precision": 0.9965608465608465,
    "recall": 0.9948051948051948,
    "f1-score": 0.9954431683900282,
    "support": 437
  },
  "weighted avg": {
    "precision": 0.9957774871962514,
    "recall": 0.9954233409610984,
    "f1-score": 0.9953729670175796,
    "support": 437
  }
}